corrosions/__init__.py
corrosions/acvg_dcvg.py
corrosions/cips.py
corrosions/const.py
corrosions/pcm.py
corrosions/sync.py
corrosions/utils.py
corrosions-0.2.0.dist-info/WHEEL
corrosions-0.2.0.dist-info/METADATA
corrosions-0.2.0.dist-info/RECORD
