Metadata-Version: 2.3
Name: corrosions
Version: 0.2.0
Summary: Corrosion calculation created by Capella Global Innovation
Author: Martanto
Author-email: Martanto <martanto@live.com>
Classifier: License :: OSI Approved :: MIT License
Classifier: Operating System :: OS Independent
Classifier: Programming Language :: Python :: 3.11
Classifier: Programming Language :: Python :: 3.12
Requires-Dist: black>=25.9.0
Requires-Dist: isort>=7.0.0
Requires-Dist: matplotlib>=3.10.7
Requires-Dist: openpyxl>=3.1.5
Requires-Dist: pandas>=2.3.3
Requires-Dist: pip>=25.3
Requires-Dist: python-slugify>=8.0.4
Requires-Dist: xlsxwriter>=3.2.9
Requires-Dist: notebook>=7.5.0
Requires-Dist: ipython
Requires-Dist: pypalettes>=0.2.1
Requires-Python: >=3.11
